{
  "hash": "a182d4c0edef7dd0c7f534c6ee0aa900",
  "result": {
    "engine": "knitr",
    "markdown": "---\nlecture: \"00 Quiz 0 fun\"\nformat: revealjs\nmetadata-files: \n  - _metadata.yml\n---\n\n\n## {{< meta lecture >}} {.large background-image=\"gfx/smooths.svg\" background-opacity=\"0.3\"}\n\n[Stat 406]{.secondary}\n\n[{{< meta author >}}]{.secondary}\n\nLast modified -- 10 September 2024\n\n\n\n\n\n$$\n\\DeclareMathOperator*{\\argmin}{argmin}\n\\DeclareMathOperator*{\\argmax}{argmax}\n\\DeclareMathOperator*{\\minimize}{minimize}\n\\DeclareMathOperator*{\\maximize}{maximize}\n\\DeclareMathOperator*{\\find}{find}\n\\DeclareMathOperator{\\st}{subject\\,\\,to}\n\\newcommand{\\E}{E}\n\\newcommand{\\Expect}[1]{\\E\\left[ #1 \\right]}\n\\newcommand{\\Var}[1]{\\mathrm{Var}\\left[ #1 \\right]}\n\\newcommand{\\Cov}[2]{\\mathrm{Cov}\\left[#1,\\ #2\\right]}\n\\newcommand{\\given}{\\ \\vert\\ }\n\\newcommand{\\X}{\\mathbf{X}}\n\\newcommand{\\x}{\\mathbf{x}}\n\\newcommand{\\y}{\\mathbf{y}}\n\\newcommand{\\P}{\\mathcal{P}}\n\\newcommand{\\R}{\\mathbb{R}}\n\\newcommand{\\norm}[1]{\\left\\lVert #1 \\right\\rVert}\n\\newcommand{\\snorm}[1]{\\lVert #1 \\rVert}\n\\newcommand{\\tr}[1]{\\mbox{tr}(#1)}\n\\newcommand{\\brt}{\\widehat{\\beta}^R_{s}}\n\\newcommand{\\brl}{\\widehat{\\beta}^R_{\\lambda}}\n\\newcommand{\\bls}{\\widehat{\\beta}_{ols}}\n\\newcommand{\\blt}{\\widehat{\\beta}^L_{s}}\n\\newcommand{\\bll}{\\widehat{\\beta}^L_{\\lambda}}\n\\newcommand{\\U}{\\mathbf{U}}\n\\newcommand{\\D}{\\mathbf{D}}\n\\newcommand{\\V}{\\mathbf{V}}\n$$\n\n\n\n\n\n## Why this class?\n\n- \"This is a required course\"\n- \"Heard it's fun!\"\n- \"I want to graduate\"\n- \"8am!\" (/s)\n- \"I want to learn a lot about ML.\"\n- \"I want to dig deeper after taking 306.\"\n- \"I want to get... more comfortable with R.\"\n- \"At first it was because everyone I knew was taking it.\"\n- \"Practical skills in preperation for future careers\"\n\n\n## Syllabus Q\n\n\n\n\n\n::: {.cell layout-align=\"center\"}\n::: {.cell-output-display}\n![](00-quiz-0-wrap_files/figure-revealjs/unnamed-chunk-1-1.svg){fig-align='center'}\n:::\n:::\n\n\n\n\n## Programming languages\n\n\n\n::: {.cell layout-align=\"center\"}\n::: {.cell-output-display}\n![](00-quiz-0-wrap_files/figure-revealjs/unnamed-chunk-2-1.svg){fig-align='center'}\n:::\n:::\n\n\n\n<!--\n## Matrix inversion\n\n\n\n::: {.cell layout-align=\"center\"}\n\n```{.r .cell-code}\nlibrary(MASS)\nX <- matrix(c(5, 3, 1, -1), nrow = 2)\nX\n```\n\n::: {.cell-output .cell-output-stdout}\n\n```\n     [,1] [,2]\n[1,]    5    1\n[2,]    3   -1\n```\n\n\n:::\n\n```{.r .cell-code}\nsolve(X)\n```\n\n::: {.cell-output .cell-output-stdout}\n\n```\n      [,1]   [,2]\n[1,] 0.125  0.125\n[2,] 0.375 -0.625\n```\n\n\n:::\n\n```{.r .cell-code}\nginv(X)\n```\n\n::: {.cell-output .cell-output-stdout}\n\n```\n      [,1]   [,2]\n[1,] 0.125  0.125\n[2,] 0.375 -0.625\n```\n\n\n:::\n\n```{.r .cell-code}\nX^(-1)\n```\n\n::: {.cell-output .cell-output-stdout}\n\n```\n          [,1] [,2]\n[1,] 0.2000000    1\n[2,] 0.3333333   -1\n```\n\n\n:::\n:::\n\n\n\n\n\n## Linear models\n\n\n\n::: {.cell layout-align=\"center\"}\n\n```{.r .cell-code}\ny <- X %*% c(2, -1) + rnorm(2)\ncoefficients(lm(y ~ X))\n```\n\n::: {.cell-output .cell-output-stdout}\n\n```\n(Intercept)          X1          X2 \n  4.8953718   0.9380314          NA \n```\n\n\n:::\n\n```{.r .cell-code}\ncoef(lm(y ~ X))\n```\n\n::: {.cell-output .cell-output-stdout}\n\n```\n(Intercept)          X1          X2 \n  4.8953718   0.9380314          NA \n```\n\n\n:::\n\n```{.r .cell-code}\nsolve(t(X) %*% X) %*% t(X) %*% y\n```\n\n::: {.cell-output .cell-output-stdout}\n\n```\n          [,1]\n[1,]  2.161874\n[2,] -1.223843\n```\n\n\n:::\n\n```{.r .cell-code}\nsolve(crossprod(X), crossprod(X, y))\n```\n\n::: {.cell-output .cell-output-stdout}\n\n```\n          [,1]\n[1,]  2.161874\n[2,] -1.223843\n```\n\n\n:::\n:::\n\n::: {.cell layout-align=\"center\"}\n\n```{.r .cell-code}\nX \\ y # this is Matlab\n```\n\n::: {.cell-output .cell-output-error}\n\n```\nError: <text>:1:3: unexpected '\\\\'\n1: X \\\n      ^\n```\n\n\n:::\n:::\n\n---\n-->\n\n## Plans\n\n::: {.cell layout-align=\"center\"}\n::: {.cell-output-display}\n![](00-quiz-0-wrap_files/figure-revealjs/unnamed-chunk-6-1.svg){fig-align='center'}\n:::\n:::\n\n## Grade predictions\n\n::: {.cell layout-align=\"center\"}\n::: {.cell-output-display}\n![](00-quiz-0-wrap_files/figure-revealjs/unnamed-chunk-7-1.svg){fig-align='center'}\n:::\n:::\n\n* 5 people say 100%\n* 18 say 90%\n* 20 say 85%\n* 41 say 80%\n",
    "supporting": [
      "00-quiz-0-wrap_files"
    ],
    "filters": [
      "rmarkdown/pagebreak.lua"
    ],
    "includes": {
      "include-after-body": [
        "\n<script>\n  // htmlwidgets need to know to resize themselves when slides are shown/hidden.\n  // Fire the \"slideenter\" event (handled by htmlwidgets.js) when the current\n  // slide changes (different for each slide format).\n  (function () {\n    // dispatch for htmlwidgets\n    function fireSlideEnter() {\n      const event = window.document.createEvent(\"Event\");\n      event.initEvent(\"slideenter\", true, true);\n      window.document.dispatchEvent(event);\n    }\n\n    function fireSlideChanged(previousSlide, currentSlide) {\n      fireSlideEnter();\n\n      // dispatch for shiny\n      if (window.jQuery) {\n        if (previousSlide) {\n          window.jQuery(previousSlide).trigger(\"hidden\");\n        }\n        if (currentSlide) {\n          window.jQuery(currentSlide).trigger(\"shown\");\n        }\n      }\n    }\n\n    // hookup for slidy\n    if (window.w3c_slidy) {\n      window.w3c_slidy.add_observer(function (slide_num) {\n        // slide_num starts at position 1\n        fireSlideChanged(null, w3c_slidy.slides[slide_num - 1]);\n      });\n    }\n\n  })();\n</script>\n\n"
      ]
    },
    "engineDependencies": {},
    "preserve": {},
    "postProcess": true
  }
}